napari_dmc_brainmap/__init__.py
napari_dmc_brainmap/napari.yaml
napari_dmc_brainmap/padding/__init__.py
napari_dmc_brainmap/padding/padding.py
napari_dmc_brainmap/params/__init__.py
napari_dmc_brainmap/params/params.py
napari_dmc_brainmap/preprocessing/__init__.py
napari_dmc_brainmap/preprocessing/preprocessing.py
napari_dmc_brainmap/preprocessing/preprocessing_tools.py
napari_dmc_brainmap/registration/__init__.py
napari_dmc_brainmap/registration/registration.py
napari_dmc_brainmap/registration/sharpy_track/__init__.py
napari_dmc_brainmap/registration/sharpy_track/__main__.py
napari_dmc_brainmap/registration/sharpy_track/sharpy_track/__init__.py
napari_dmc_brainmap/registration/sharpy_track/sharpy_track/controller/__init__.py
napari_dmc_brainmap/registration/sharpy_track/sharpy_track/controller/status.py
napari_dmc_brainmap/registration/sharpy_track/sharpy_track/images/__init__.py
napari_dmc_brainmap/registration/sharpy_track/sharpy_track/images/crosshair_red.png
napari_dmc_brainmap/registration/sharpy_track/sharpy_track/images/crosshair_yellow.png
napari_dmc_brainmap/registration/sharpy_track/sharpy_track/images/crosshair_yellow_0.png
napari_dmc_brainmap/registration/sharpy_track/sharpy_track/images/crosshair_yellow_s.png
napari_dmc_brainmap/registration/sharpy_track/sharpy_track/images/empty.png
napari_dmc_brainmap/registration/sharpy_track/sharpy_track/images/error_red.png
napari_dmc_brainmap/registration/sharpy_track/sharpy_track/images/keyboard_shortcuts.png
napari_dmc_brainmap/registration/sharpy_track/sharpy_track/model/AtlasModel.py
napari_dmc_brainmap/registration/sharpy_track/sharpy_track/model/HelperModel.py
napari_dmc_brainmap/registration/sharpy_track/sharpy_track/model/MeasurementHandler.py
napari_dmc_brainmap/registration/sharpy_track/sharpy_track/model/PandasModel.py
napari_dmc_brainmap/registration/sharpy_track/sharpy_track/model/__init__.py
napari_dmc_brainmap/registration/sharpy_track/sharpy_track/model/calculation.py
napari_dmc_brainmap-0.1.7b12.dist-info/licenses/LICENSE.txt
napari_dmc_brainmap-0.1.7b12.dist-info/METADATA
napari_dmc_brainmap-0.1.7b12.dist-info/WHEEL
napari_dmc_brainmap-0.1.7b12.dist-info/entry_points.txt
napari_dmc_brainmap-0.1.7b12.dist-info/top_level.txt
napari_dmc_brainmap-0.1.7b12.dist-info/RECORD
