Metadata-Version: 2.4
Name: napari-dmc-brainmap
Version: 0.1.7b12
Summary: DMC-BrainMap is an end-to-end tool for multi-feature brain mapping across species
Author: Felix Jung
Author-email: jung.neurosc@gmail.com
License: BSD-3-Clause
Classifier: Development Status :: 4 - Beta
Classifier: Framework :: napari
Classifier: Intended Audience :: Developers
Classifier: License :: OSI Approved :: BSD License
Classifier: Operating System :: OS Independent
Classifier: Programming Language :: Python
Classifier: Programming Language :: Python :: 3
Classifier: Programming Language :: Python :: 3 :: Only
Classifier: Programming Language :: Python :: 3.10
Classifier: Topic :: Scientific/Engineering :: Image Processing
Requires-Python: ==3.10.*
License-File: LICENSE.txt
Requires-Dist: numpy==1.26.4
Requires-Dist: pandas==2.0.1
Requires-Dist: matplotlib==3.8.3
Requires-Dist: seaborn==0.12.2
Requires-Dist: scikit-learn==1.4.1.post1
Requires-Dist: scikit-image==0.22.0
Requires-Dist: scikit-spatial==7.2.0
Requires-Dist: tifffile==2023.2.28
Requires-Dist: magicgui==0.8.1
Requires-Dist: qtpy==2.4.1
Requires-Dist: opencv-python==4.9.0.80
Requires-Dist: natsort==8.4.0
Requires-Dist: imagecodecs==2024.1.1
Requires-Dist: mergedeep==1.3.4
Requires-Dist: aicsimageio==4.14.0
Requires-Dist: aicspylibczi==3.1.2
Requires-Dist: aicssegmentation==0.5.3
Requires-Dist: distinctipy==1.3.4
Requires-Dist: bg_atlasapi==1.0.2
Requires-Dist: shapely==2.0.1
Dynamic: license-file
